hubspot_mcp_server/__init__.py
hubspot_mcp_server/server.py
hubspot_mcp_server-0.1.1.dist-info/licenses/LICENSE.md
hubspot_mcp_server-0.1.1.dist-info/METADATA
hubspot_mcp_server-0.1.1.dist-info/WHEEL
hubspot_mcp_server-0.1.1.dist-info/entry_points.txt
hubspot_mcp_server-0.1.1.dist-info/top_level.txt
hubspot_mcp_server-0.1.1.dist-info/RECORD
