Metadata-Version: 2.4
Name: hubspot-mcp-server
Version: 0.1.1
Summary: A simple MCP server for interacting with the HubSpot API
Author-email: Isaac Raja <isaacraja@gmail.com>
License-Expression: MIT
Classifier: Programming Language :: Python :: 3
Classifier: Operating System :: OS Independent
Requires-Python: >=3.10
License-File: LICENSE.md
Requires-Dist: mcp[cli]>=1.5.0
Requires-Dist: httpx>=0.25.0
Provides-Extra: test
Requires-Dist: pytest>=7.3.1; extra == "test"
Requires-Dist: pytest-cov>=4.1.0; extra == "test"
Requires-Dist: pytest-mock>=3.10.0; extra == "test"
Requires-Dist: requests-mock>=1.10.0; extra == "test"
Requires-Dist: pytest-asyncio>=0.23.0; extra == "test"
Provides-Extra: dev
Requires-Dist: ruff>=0.11.0; extra == "dev"
Dynamic: license-file
